use_nacos/__init__.py
use_nacos/_chooser.py
use_nacos/cache.py
use_nacos/client.py
use_nacos/endpoints/__init__.py
use_nacos/endpoints/config.py
use_nacos/endpoints/endpoint.py
use_nacos/endpoints/instance.py
use_nacos/endpoints/namespace.py
use_nacos/endpoints/service.py
use_nacos/exception.py
use_nacos/helper.py
use_nacos/serializer.py
use_nacos/typings.py
use_nacos-0.1.6.dist-info/METADATA
use_nacos-0.1.6.dist-info/WHEEL
use_nacos-0.1.6.dist-info/RECORD
