Metadata-Version: 2.3
Name: use-nacos
Version: 0.1.6
Summary: A python nacos client based on the official open-api
License: MIT
Author: MicLon
Author-email: jcnd@163.com
Requires-Python: >=3.8,<4.0
Classifier: License :: OSI Approved :: MIT License
Classifier: Programming Language :: Python :: 3
Classifier: Programming Language :: Python :: 3.8
Classifier: Programming Language :: Python :: 3.9
Classifier: Programming Language :: Python :: 3.10
Classifier: Programming Language :: Python :: 3.11
Classifier: Programming Language :: Python :: 3.12
Classifier: Programming Language :: Python :: 3.13
Requires-Dist: httpx (>=0.27.0,<1.0.0)
Requires-Dist: tomli (>=2.0.0,<3.0.0) ; python_version < "3.11"
Project-URL: Bug Tracker, https://github.com/use-py/use-nacos/issues
Project-URL: Homepage, https://github.com/use-py/use-nacos
Project-URL: Repository, https://github.com/use-py/use-nacos
